[
  {
    "id": 1,
    "title": "Recliner Chair Wood",
    "price": 149.99,
    "previousPrice": 187.49,
    "sale": "20% OFF",
    "description": "It has a backrest that can be tilted back, and often a footrest extended",
    "image": "https://i.postimg.cc/XYPtBjjd/image-125-removebg-preview-1.png"
  },
  {
    "id": 2,
    "title": "Timber Ride Padded",
    "price": 299.99,
    "previousPrice": 352.93,
    "sale": "15% OFF",
    "description": "High Back Rocking Side Pocket Portable Folding Outdoor Camping Chairs",
    "image": "https://i.postimg.cc/CKfXj35t/rocking-chair-with-padded-seat-1.png"
  },
  {
    "id": 3,
    "title": "Blank Bamboo Wicker",
    "price": 399.99,
    "previousPrice": 533.32,
    "sale": "25% OFF",
    "description": "Lightweight, easy to clean, sturdy, safe and stable. Non-slip legs",
    "image": "https://i.postimg.cc/3xNPw4T3/image-147.png"
  },
  {
    "id": 4,
    "title": "Isolated Wooden Rock",
    "price": 199.99,
    "previousPrice": 222.21,
    "sale": "10% OFF",
    "description": "It has a backrest that can be tilted back, and often a footrest extended",
    "image": "https://i.postimg.cc/bNz7KVVD/image-148.png"
  },
  {
    "id": 5,
    "title": "Colored Wooden Chair",
    "price": 249.99,
    "previousPrice": 357.13,
    "sale": "30% OFF",
    "description": "It has a backrest that can be tilted back, and often a footrest extended",
    "image": "https://i.postimg.cc/4NBDZvj8/image-146.png"
  },
  {
    "id": 6,
    "title": "Minimal Empty Rocking",
    "price": 89.99,
    "previousPrice": 112.49,
    "sale": "20% OFF",
    "description": "A seat, especially for one person, usually having four legs for support.",
    "image": "https://i.postimg.cc/L4BdQFDF/image-149.png"
  }
]
